sokort/__init__.py
sokort/__main__.py
sokort/_data_finder.py
sokort/_loader.py
sokort/_logging.py
sokort/_plotter.py
sokort/_presenter.py
sokort/_util.py
sokort/config.py
sokort/convert_image.sh
sokort/interface.py
sokort/load_env.sh
sokort/systems/__init__.py
sokort/systems/grapes_gfs_gmf/__init__.py
sokort/systems/grapes_gfs_gmf/_plotter.py
sokort/systems/grapes_gfs_gmf/run_ncl.sh
sokort/systems/grapes_gfs_gmf/graphics/__init__.py
sokort/systems/grapes_gfs_gmf/graphics/an_aea/__init__.py
sokort/systems/grapes_gfs_gmf/graphics/an_aea/cape_sfc_an_aea.py
sokort/systems/grapes_gfs_gmf/graphics/an_aea/cdbz_sfc_an_aea.py
sokort/systems/grapes_gfs_gmf/graphics/an_aea/k_sfc_an_aea.py
sokort/systems/grapes_gfs_gmf/graphics/an_aea/pte_p700_an_aea.py
sokort/systems/grapes_gfs_gmf/graphics/an_aea/pte_p850_an_aea.py
sokort/systems/grapes_gfs_gmf/graphics/an_aea/pwat_sfc_an_aea.py
sokort/systems/grapes_gfs_gmf/graphics/an_aea/qflx_div_p700_an_aea.py
sokort/systems/grapes_gfs_gmf/graphics/an_aea/qflx_div_p850_an_aea.py
sokort/systems/grapes_gfs_gmf/graphics/an_aea/qflx_p700_an_aea.py
sokort/systems/grapes_gfs_gmf/graphics/an_aea/qflx_p850_an_aea.py
sokort/systems/grapes_gfs_gmf/graphics/an_aea/rh2m_sfc_an_aea.py
sokort/systems/grapes_gfs_gmf/graphics/an_aea/t2m_sfc_an_aea.py
sokort/systems/grapes_gfs_gmf/graphics/an_aea/tadv_p500_an_aea.py
sokort/systems/grapes_gfs_gmf/graphics/an_aea/tadv_p850_an_aea.py
sokort/systems/grapes_gfs_gmf/graphics/an_aea/voradv_p500_an_aea.py
sokort/systems/grapes_gfs_gmf/graphics/fc_aea/__init__.py
sokort/systems/grapes_gfs_gmf/graphics/fc_aea/hgt_p500_fc_aea.py
sokort/systems/grapes_gfs_gmf/graphics/fc_aea/hgt_p500_mslp_sfc_fc_aea.py
sokort/systems/grapes_gfs_gmf/graphics/fc_aea/hgt_p500_wind_p850_fc_aea.py
sokort/systems/grapes_gfs_gmf/graphics/fc_aea/mslp_sfc_fc_aea.py
sokort/systems/grapes_gfs_gmf/graphics/fc_aea/qv_p700_fc_aea.py
sokort/systems/grapes_gfs_gmf/graphics/fc_aea/qv_p850_fc_aea.py
sokort-0.4.2.dist-info/LICENSE.md
sokort-0.4.2.dist-info/METADATA
sokort-0.4.2.dist-info/WHEEL
sokort-0.4.2.dist-info/top_level.txt
sokort-0.4.2.dist-info/RECORD
